LICENSE
MANIFEST.in
README.md
README.txt
setup.py
sqoot/__init__.py
sqoot.egg-info/PKG-INFO
sqoot.egg-info/SOURCES.txt
sqoot.egg-info/dependency_links.txt
sqoot.egg-info/requires.txt
sqoot.egg-info/top_level.txt
sqoot.egg-info/zip-safe
sqoot/tests/__init__.py
sqoot/tests/_creds.example.py
sqoot/tests/test_categories.py
sqoot/tests/test_clicks.py
sqoot/tests/test_commissions.py
sqoot/tests/test_coupons.py
sqoot/tests/test_deals.py
sqoot/tests/test_merchants.py
sqoot/tests/test_providers.py