Metadata-Version: 1.0
Name: sqoot
Version: 20140727
Summary: Sqoot wrapper library
Home-page: https://github.com/ragarwal6397
Author: Rajat Agarwal
Author-email: rajatagarwal@alumni.purdue.edu
License: MIT License
Download-URL: https://github.com/ragarwal6397/sqoot/tarball/master
Keywords: sqoot api
Platform: UNKNOWN
Classifier: Development Status :: 5 - Production/Stable
Classifier: Intended Audience :: Developers
Classifier: Natural Language :: English
Classifier: Operating System :: OS Independent
Classifier: Programming Language :: Python
Classifier: Topic :: Internet :: WWW/HTTP :: Dynamic Content
Classifier: License :: OSI Approved :: MIT License
